pyapetnet/.gitignore
pyapetnet/__init__.py
pyapetnet/generators.py
pyapetnet/losses.py
pyapetnet/models.py
pyapetnet/preprocessing.py
pyapetnet/registration.py
pyapetnet/utils.py
pyapetnet/scripts/list_models.py
pyapetnet/scripts/predict_from_dicom.py
pyapetnet/scripts/predict_from_nifti.py
pyapetnet/trained_models/model_description.md
pyapetnet/trained_models/190528_paper_bet_10_psf_mlem/config.json
pyapetnet/trained_models/190528_paper_bet_10_psf_mlem/saved_model.pb
pyapetnet/trained_models/190528_paper_bet_10_psf_mlem/variables/variables.data-00000-of-00001
pyapetnet/trained_models/190528_paper_bet_10_psf_mlem/variables/variables.index
pyapetnet/trained_models/200824_mae_osem_nopsf_bet_10/config.json
pyapetnet/trained_models/200824_mae_osem_nopsf_bet_10/saved_model.pb
pyapetnet/trained_models/200824_mae_osem_nopsf_bet_10/variables/variables.data-00000-of-00001
pyapetnet/trained_models/200824_mae_osem_nopsf_bet_10/variables/variables.index
pyapetnet/trained_models/200824_mae_osem_psf_bet_10/config.json
pyapetnet/trained_models/200824_mae_osem_psf_bet_10/saved_model.pb
pyapetnet/trained_models/200824_mae_osem_psf_bet_10/variables/variables.data-00000-of-00001
pyapetnet/trained_models/200824_mae_osem_psf_bet_10/variables/variables.index
pyapetnet/trained_models/S1_osem_b10_fdg/config.json
pyapetnet/trained_models/S1_osem_b10_fdg/log.csv
pyapetnet/trained_models/S1_osem_b10_fdg/models.py
pyapetnet/trained_models/S1_osem_b10_fdg/saved_model.pb
pyapetnet/trained_models/S1_osem_b10_fdg/variables/variables.data-00000-of-00001
pyapetnet/trained_models/S1_osem_b10_fdg/variables/variables.index
pyapetnet/trained_models/S2_osem_b10_fdg_pe2i/config.json
pyapetnet/trained_models/S2_osem_b10_fdg_pe2i/log.csv
pyapetnet/trained_models/S2_osem_b10_fdg_pe2i/models.py
pyapetnet/trained_models/S2_osem_b10_fdg_pe2i/saved_model.pb
pyapetnet/trained_models/S2_osem_b10_fdg_pe2i/variables/variables.data-00000-of-00001
pyapetnet-1.5.6.dist-info/LICENSE
pyapetnet-1.5.6.dist-info/METADATA
pyapetnet-1.5.6.dist-info/WHEEL
pyapetnet-1.5.6.dist-info/entry_points.txt
pyapetnet-1.5.6.dist-info/top_level.txt
pyapetnet-1.5.6.dist-info/RECORD
