Metadata-Version: 2.2
Name: pyapetnet
Version: 1.5.6
Summary: CNN for anatomy-guided PET reconstruction
Author-email: Georg Schramm <georg.schramm@kuleuven.be>
License: MIT
Project-URL: Homepage, https://github.com/gschramm/pyapetnet
Classifier: License :: OSI Approved :: MIT License
Classifier: Operating System :: OS Independent
Classifier: Programming Language :: Python :: 3
Requires-Python: >=3.9
License-File: LICENSE
Requires-Dist: SimpleITK~=2.0
Requires-Dist: pymirc~=0.29
Requires-Dist: click~=8.0
Requires-Dist: tensorflow<=2.15
